SmileGAN/Smile_GAN_clustering.py
SmileGAN/__init__.py
SmileGAN/clustering.py
SmileGAN/data_loading.py
SmileGAN/evaluate.py
SmileGAN/model.py
SmileGAN/modules.py
SmileGAN/networks.py
SmileGAN/utils.py
SmileGAN-0.1.3.dist-info/LICENSE
SmileGAN-0.1.3.dist-info/METADATA
SmileGAN-0.1.3.dist-info/WHEEL
SmileGAN-0.1.3.dist-info/top_level.txt
SmileGAN-0.1.3.dist-info/RECORD
