Metadata-Version: 2.1
Name: SmileGAN
Version: 0.1.3
Summary: A python implementation of Smile-GAN for semisupervised clustering
Home-page: https://github.com/zhijian-yang/SmileGAN
Author: zhijian.yang
Author-email: zhijianyang@outlook.com
Classifier: Programming Language :: Python :: 3
Classifier: License :: OSI Approved :: MIT License
Classifier: Operating System :: OS Independent
License-File: LICENSE
Requires-Dist: numpy (>=1.22.3)
Requires-Dist: tqdm (>=4.50.2)
Requires-Dist: torch (==1.10.2)
Requires-Dist: scikit-learn (>=0.24.2)
Requires-Dist: scipy (>=1.8.0)
Requires-Dist: pandas (>=1.4.2)
